[
    {
        "id": "14864910",
        "enabled": true,
        "name": "Downtown Fitness Hub",
        "description": "State-of-the-art fitness center in the heart of downtown. Our gym offers the latest equipment, personal training, and various fitness classes. Open 24/7 for your convenience. We provide a clean and welcoming environment to help you reach your fitness goals. From weightlifting to cardio machines, we have it all.",
        "activity_type": "Public Spot",
        "sport_type": "weight-lifter",
        "price": {"value": 50, "unit": "$"},
        "location": {
            "country": "Germany",
            "area": "Berlin",
            "city": "Berlin",
            "smart_location": "Berlin, Germany",
            "geometry": {
                "type": "Point",
                "coordinates": {"latitude": 13.362449647584155, "longitude": 52.48895019165655}
            }
        },
        "participants": {"current": 240, "max": null},
        "reviews": {"number_of_reviews": 14, "review_scores_rating": 100},
        "pictures": ["https://ironberg.com.br/assets/images/ironberg-sp-3.jpeg"],
        "host": {
            "host_picture_url": "https://a0.muscache.com/im/pictures/43518019/ead2dbb7_original.jpg?aki_policy=x_large",
            "host_name": "Monica",
            "host_since": "2015-06-15"
        },
        "datetimes": {
            "datetime_created": "2024-09-15T12:00:00Z",
            "datetime_deleted": null,
            "datetime_start": "2024-09-15T09:00:00Z",
            "datetime_finish": "2024-09-15T18:00:00Z"
        }
    },
    {
        "id": "3393282",
        "enabled": true,
        "name": "Evening Yoga Class",
        "description": "Unwind with our evening yoga session. Experience a gentle flow designed to release tension, calm your mind, and prepare your body for restful sleep. Our experienced instructor will guide you through a series of poses and breathing exercises tailored to all skill levels. Whether you're looking to de-stress after a long day or enhance your overall well-being, this session offers the perfect balance of relaxation and rejuvenation. Join us and embrace the peaceful ambiance, leaving you refreshed and ready for the day ahead.",
        "activity_type": "Session",
        "sport_type": "yoga",
        "price": {"value": 75, "unit": "$"},
        "location": {
            "country": "Germany",
            "area": "Berlin",
            "city": "Berlin",
            "smart_location": "Berlin, Germany",
            "geometry": {
                "type": "Point",
                "coordinates": {"latitude": 13.36255769672526, "longitude": 52.548872817489354}
            }
        },
        "participants": {"current": 2, "max": null},
        "reviews": {"number_of_reviews": 18, "review_scores_rating": 99},
        "pictures": [
            "https://www.ymcaclub.co.uk/wp-content/uploads/2023/05/Supple_Strenght-34-1024x684.jpg"
        ],
        "host": {
            "host_picture_url": "https://a0.muscache.com/im/users/17119078/profile_pic/1403904832/original.jpg?aki_policy=profile_x_medium",
            "host_name": "Stefanie",
            "host_since": "2014-06-22"
        },
        "datetimes": {
            "datetime_created": "2024-09-15T12:00:00Z",
            "datetime_deleted": null,
            "datetime_start": "2024-09-15T17:00:00Z",
            "datetime_finish": "2024-09-15T18:30:00Z"
        }
    },
    {
        "id": "7885622",
        "enabled": true,
        "name": "Newbie Soccer Cup",
        "description": "Join us for the inaugural Newbee Soccer Cup, a thrilling new sports event designed to bring together soccer enthusiasts of all skill levels! This exciting tournament offers a platform for amateur teams to showcase their talent, compete in a friendly yet competitive environment, and foster a sense of community and sportsmanship.",
        "activity_type": "Event",
        "sport_type": "soccer",
        "price": {"value": 50, "unit": "$"},
        "location": {
            "country": "Germany",
            "area": "Berlin",
            "city": "Berlin",
            "smart_location": "Berlin, Germany",
            "geometry": {
                "type": "Point",
                "coordinates": {"latitude": 13.456734695054609, "longitude": 52.514191929150456}
            }
        },
        "participants": {"current": 23, "max": null},
        "reviews": {"number_of_reviews": 38, "review_scores_rating": 99},
        "pictures": [
            "https://s2-ge.glbimg.com/AApE5gEe4YHuPloai7nojxAoTug=/0x0:719x476/984x0/smart/filters:strip_icc()/s.glbimg.com/es/ge/f/original/2014/09/21/final_copa_oeste.jpg"
        ],
        "host": {
            "host_picture_url": "https://a0.muscache.com/im/pictures/0acc35e0-67b3-4a80-b257-56052b290f1e.jpg?aki_policy=profile_x_medium",
            "host_name": "Mikael",
            "host_since": "2015-02-22"
        },
        "datetimes": {
            "datetime_created": "2024-09-15T12:00:00Z",
            "datetime_deleted": null,
            "datetime_start": "2024-09-15T10:00:00Z",
            "datetime_finish": "2024-09-15T16:00:00Z"
        }
    },
    {
        "id": "1563562",
        "enabled": true,
        "name": "IronMan Delray",
        "description": "Challenge yourself with the ultimate endurance event at IronMan Delray. Set against the beautiful backdrop of Delray Beach, this triathlon pushes athletes to their limits with a grueling combination of swimming, cycling, and running. Whether you're a seasoned triathlete or taking on your first IronMan, this event offers a supportive and electrifying atmosphere. With well-marked courses, top-notch facilities, and enthusiastic spectators, IronMan Delray promises an unforgettable experience that will test your strength, stamina, and determination. Finish strong and earn your place among the IronMan elite.",
        "activity_type": "Event",
        "sport_type": "run-fast",
        "price": {"value": 45, "unit": "$"},
        "location": {
            "country": "Germany",
            "area": "Berlin",
            "city": "Berlin",
            "smart_location": "Berlin, Germany",
            "geometry": {
                "type": "Point",
                "coordinates": {"latitude": 13.34589882667451, "longitude": 52.499586830677025}
            }
        },
        "participants": {"current": 43, "max": null},
        "reviews": {"number_of_reviews": 71, "review_scores_rating": 96},
        "pictures": ["https://orkilacapital.com/wp-content/uploads/2023/09/IM-Finish.jpg"],
        "host": {
            "host_picture_url": "https://a0.muscache.com/im/users/8319062/profile_pic/1402827631/original.jpg?aki_policy=profile_x_medium",
            "host_name": "Sven",
            "host_since": "2013-08-22"
        },
        "datetimes": {
            "datetime_created": "2024-09-15T12:00:00Z",
            "datetime_deleted": null,
            "datetime_start": "2024-09-15T07:00:00Z",
            "datetime_finish": "2024-09-15T15:00:00Z"
        }
    }
]
